JingtongPandasTansuoxingFenxiChuyi/README.md
JingtongPandasTansuoxingFenxiChuyi/__init__.py
JingtongPandasTansuoxingFenxiChuyi/__main__.py
JingtongPandasTansuoxingFenxiChuyi/file.epub
JingtongPandasTansuoxingFenxiChuyi/index.html
JingtongPandasTansuoxingFenxiChuyi/css/__init__.py
JingtongPandasTansuoxingFenxiChuyi/css/annotations.css
JingtongPandasTansuoxingFenxiChuyi/css/main.css
JingtongPandasTansuoxingFenxiChuyi/css/normalize.css
JingtongPandasTansuoxingFenxiChuyi/css/popup.css
JingtongPandasTansuoxingFenxiChuyi/font/__init__.py
JingtongPandasTansuoxingFenxiChuyi/font/fontello.eot
JingtongPandasTansuoxingFenxiChuyi/font/fontello.svg
JingtongPandasTansuoxingFenxiChuyi/font/fontello.ttf
JingtongPandasTansuoxingFenxiChuyi/font/fontello.woff
JingtongPandasTansuoxingFenxiChuyi/img/__init__.py
JingtongPandasTansuoxingFenxiChuyi/img/annotator-glyph-sprite.png
JingtongPandasTansuoxingFenxiChuyi/img/annotator-icon-sprite.png
JingtongPandasTansuoxingFenxiChuyi/img/apple-touch-icon.png
JingtongPandasTansuoxingFenxiChuyi/img/cancelfullscreen.png
JingtongPandasTansuoxingFenxiChuyi/img/close.png
JingtongPandasTansuoxingFenxiChuyi/img/fullscreen.png
JingtongPandasTansuoxingFenxiChuyi/img/loader.gif
JingtongPandasTansuoxingFenxiChuyi/img/menu-icon.png
JingtongPandasTansuoxingFenxiChuyi/img/save.png
JingtongPandasTansuoxingFenxiChuyi/img/saved.png
JingtongPandasTansuoxingFenxiChuyi/img/settings-s.png
JingtongPandasTansuoxingFenxiChuyi/img/settings.png
JingtongPandasTansuoxingFenxiChuyi/img/star.png
JingtongPandasTansuoxingFenxiChuyi/js/__init__.py
JingtongPandasTansuoxingFenxiChuyi/js/epub.js
JingtongPandasTansuoxingFenxiChuyi/js/epub.min.js
JingtongPandasTansuoxingFenxiChuyi/js/epub.min.map
JingtongPandasTansuoxingFenxiChuyi/js/hooks.min.js
JingtongPandasTansuoxingFenxiChuyi/js/hooks.min.map
JingtongPandasTansuoxingFenxiChuyi/js/reader.js
JingtongPandasTansuoxingFenxiChuyi/js/reader.js.map
JingtongPandasTansuoxingFenxiChuyi/js/reader.min.js
jingtong_pandas_tansuoxing_fenxi_chuyi-2024.3.5.0.dist-info/METADATA
jingtong_pandas_tansuoxing_fenxi_chuyi-2024.3.5.0.dist-info/WHEEL
jingtong_pandas_tansuoxing_fenxi_chuyi-2024.3.5.0.dist-info/entry_points.txt
jingtong_pandas_tansuoxing_fenxi_chuyi-2024.3.5.0.dist-info/top_level.txt
jingtong_pandas_tansuoxing_fenxi_chuyi-2024.3.5.0.dist-info/RECORD
